{
  "characters": [
    {
      "id": "knight",
      "name": "Knight",
      "base": "Kinght.smd",
      "files": [
        "kin125.smd",
        "kin128.smd",
        "kina4a.tga",
        "kina4b.tga",
        "kina4c.tga",
        "kinaflam.smd",
        "kinaflam.tga",
        "kinajapa.smd",
        "kinapalm.smd",
        "kinapalm.tga",
        "Kinght.smd",
        "Kinght1.smd",
        "Kinght2.smd",
        "KINLPK.smd",
        "KINLPK_1.TGA",
        "KINLPK_2.TGA",
        "KINLPK_3.tga",
        "kinvip.smd",
        "ks-1-ma.Bmp",
        "ks-1.Bmp",
        "KS-175-InFernoPT.smd",
        "ks-175105.tga",
        "ks-175105b.bmp",
        "ks-175105c.tga",
        "ks-175cap.bmp",
        "ks-175shl.bmp",
        "ks-2.Bmp",
        "ks-3.bmp",
        "ks-3.tga",
        "ks-hair1.smd",
        "ks-hair2.smd",
        "KS-HairS.smd",
        "ks150.Bmp",
        "ks150.smd",
        "ks151.Bmp",
        "ks151a.Bmp",
        "ks153.tga",
        "KS1751.bmp",
        "ks_drago1.bmp",
        "ks_drago2.bmp",
        "ks_drago3.tga",
        "ks_dragon.smd",
        "ks_TMUSA_WC.tga",
        "kshair.smd",
        "KSMaskCelestial.bmp",
        "KsMsk.bmp",
        "ksxmas.smd",
        "SPK_ARMOR_KS.dds"
      ],
      "smdFiles": [
        "kin125.smd",
        "kin128.smd",
        "kinaflam.smd",
        "kinajapa.smd",
        "kinapalm.smd",
        "Kinght.smd",
        "Kinght1.smd",
        "Kinght2.smd",
        "KINLPK.smd",
        "kinvip.smd",
        "KS-175-InFernoPT.smd",
        "ks-hair1.smd",
        "ks-hair2.smd",
        "KS-HairS.smd",
        "ks150.smd",
        "ks_dragon.smd",
        "kshair.smd",
        "ksxmas.smd"
      ],
      "defaultModel": "kin125.smd"
    },
    {
      "id": "fighter",
      "name": "Fighter",
      "base": "Lutador.smd",
      "files": [
        "fs armor congelada1.tga",
        "fs armor herra2.tga",
        "FS-175-InFernoPT.smd",
        "FS-175a.bmp",
        "fs-hair1.smd",
        "fs-hair2.smd",
        "FS-HairS.smd",
        "fs01.bmp",
        "fs150.bmp",
        "fs150.smd",
        "fs150a.Bmp",
        "fs152.Bmp",
        "fs153.BMP",
        "fs301.smd",
        "FS61.bmp",
        "FS62.bmp",
        "FS71.BMP",
        "FS72.bmp",
        "FS73.BMP",
        "fshair.smd",
        "FsMask.bmp",
        "FsMaskCelestial.bmp",
        "fsxmas.smd",
        "lut125.smd",
        "lut128.smd",
        "Lutador.smd",
        "Lutador1.smd",
        "Lutador2.smd",
        "LutaLPK.smd",
        "LutaLPK1.TGA",
        "LutaLPK2.tga",
        "LutaLPK3.TGA",
        "lutvip.smd"
      ],
      "smdFiles": [
        "FS-175-InFernoPT.smd",
        "fs-hair1.smd",
        "fs-hair2.smd",
        "FS-HairS.smd",
        "fs150.smd",
        "fs301.smd",
        "fshair.smd",
        "fsxmas.smd",
        "lut125.smd",
        "lut128.smd",
        "Lutador.smd",
        "Lutador1.smd",
        "Lutador2.smd",
        "LutaLPK.smd",
        "lutvip.smd"
      ],
      "defaultModel": "Lutador1.smd"
    },
    {
      "id": "mechanician",
      "name": "Mechanician",
      "base": "Mecanico.smd",
      "files": [
        "mec125.smd",
        "mec128.smd",
        "meca4a.tga",
        "meca4b.tga",
        "meca4c.tga",
        "meca_054_01.tga",
        "meca_054_02.tga",
        "meca_054_03.tga",
        "meca_055_01.tga",
        "meca_055_02.tga",
        "meca_055_03.tga",
        "meca_108_01.tga",
        "meca_108_02.tga",
        "meca_108_03.tga",
        "meca_108_58.tga",
        "meca_108_59.tga",
        "meca_108_60.tga",
        "meca_125_01.tga",
        "meca_125_02.tga",
        "meca_125_03.tga",
        "meca_125_04.tga",
        "meca_125_05.tga",
        "meca_125_06.tga",
        "meca_125_07.tga",
        "meca_125_08.tga",
        "meca_125_09.tga",
        "meca_125_0X.tga",
        "meca_125_0Y.tga",
        "meca_125_0Z.tga",
        "meca_12b_01.tga",
        "meca_12b_02.tga",
        "meca_12b_03.tga",
        "meca_12z_z1.tga",
        "meca_12z_z2.tga",
        "meca_12z_z3.tga",
        "meca_166_01.tga",
        "meca_166_02.tga",
        "meca_166_03.tga",
        "meca_Argen_WC.tga",
        "meca_Argnt_WC.tga",
        "meca_Bahia_WC.tga",
        "meca_Brazil_WC.tga",
        "meca_Brzil_WC.tga",
        "meca_chels_EG.tga",
        "meca_Chile_WC.tga",
        "meca_chinadress.tga",
        "meca_Colom_WC.tga",
        "meca_exc_01.tga",
        "meca_exc_02.tga",
        "meca_exc_03.tga",
        "meca_Franc_WC.tga",
        "meca_Germa_WC.tga",
        "meca_hanbok01.tga",
        "meca_hanbok02.tga",
        "meca_Holla_WC.tga",
        "meca_Italy_WC.tga",
        "meca_Japan_WC.tga",
        "meca_kimono.tga",
        "meca_magic_103_01.tga",
        "meca_magic_103_02.tga",
        "meca_magic_103_03.tga",
        "meca_magic_455_01.tga",
        "meca_magic_455_02.tga",
        "meca_magic_455_03.tga",
        "meca_magic_x55_01.tga",
        "meca_magic_x55_02.tga",
        "meca_magic_x55_03.tga",
        "meca_manch_EG.tga",
        "meca_Mexic_WC.tga",
        "meca_P_han.tga",
        "meca_Peru_WC.tga",
        "meca_Peruu_WC.tga",
        "meca_Pinoy_WC.tga",
        "meca_Portu_WC.tga",
        "meca_pugi.tga",
        "meca_Santa.tga",
        "meca_Santa_G.tga",
        "meca_soldier_B.tga",
        "meca_Spain_WC.tga",
        "meca_swim.tga",
        "meca_TMUSA_WC.tga",
        "meca_traje_U.tga",
        "meca_trajeMA.tga",
        "meca_Vietn_WC.tga",
        "meca_WC.bmp",
        "meca_WC.tga",
        "meca_wmelon.tga",
        "mecaKT_01.tga",
        "mecaKT_01b.tga",
        "mecaKT_02.tga",
        "mecaKT_02b.tga",
        "mecaKT_03.tga",
        "mecaKT_03b.tga",
        "Mecanico.smd",
        "Mecanico1.smd",
        "Mecanico2.smd",
        "mecasb_01.tga",
        "mecasb_01b.tga",
        "mecasb_02.tga",
        "mecasb_02b.tga",
        "mecasb_03.tga",
        "mecasb_03b.tga",
        "mecaSF_01.tga",
        "mecaSF_01b.tga",
        "mecaSF_02.tga",
        "mecaSF_02b.tga",
        "mecaSF_03.tga",
        "mecaSF_03b.tga",
        "mecaSF_11b.tga",
        "mecaSF_12b.tga",
        "mecaSF_13.tga",
        "mecaSG_01.tga",
        "mecaSG_01b.tga",
        "mecaSG_02.tga",
        "mecaSG_02b.tga",
        "mecaSG_03.tga",
        "mecaSG_03b.tga",
        "mecasy_01.tga",
        "mecasy_01b.tga",
        "mecasy_02.tga",
        "mecasy_02b.tga",
        "mecasy_03.tga",
        "mecasy_03b.tga",
        "mecasz_01.tga",
        "mecasz_01b.tga",
        "mecasz_02.tga",
        "mecasz_02b.tga",
        "mecasz_03.tga",
        "mecasz_03b.tga",
        "mech301.smd",
        "mechanic hairtint_M.tga",
        "mechanic hairtint_W.tga",
        "mechanic_Aan.tga",
        "mechanic_Aan2.tga",
        "mechanic_ma1.tga",
        "mechanic_mab.tga",
        "mechanic_man.tga",
        "mechanic_man2.tga",
        "mechanic_manb.tga",
        "MechLPK.smd",
        "MechLPK1.TGA",
        "MechLPK2.TGA",
        "MechLPK3.TGA",
        "mecvip.smd",
        "megisy_02b.tga",
        "megisz_02c.tga",
        "ms-1.tga",
        "MS-175-a-105a.bmp",
        "MS-175105a.bmp",
        "MS-175ha-105a.tga",
        "MS-175ha-105b.tga",
        "ms-2.bmp",
        "ms-3.tga",
        "ms-hair1.smd",
        "ms-hair2.smd",
        "MS-HairS.smd",
        "ms150.smd",
        "ms151.tga",
        "ms152.bmp",
        "ms152a.bmp",
        "ms152b.bmp",
        "ms152c.bmp",
        "ms153.tga",
        "MS175-105.bmp",
        "MS1751.bmp",
        "MS175105.bmp",
        "ms_dragon.smd",
        "MsE219.tga",
        "MsE320.tga",
        "MsE420.tga",
        "MsE521.tga",
        "mshair.smd",
        "Mshe01.tga",
        "Mshe03.tga",
        "Mshe09.tga",
        "Mshe12.tga",
        "Mshe15.tga",
        "Mshe18.tga",
        "Mshe19.tga",
        "Mshe20.tga",
        "Mshe21.tga",
        "Mshe22.TGA",
        "Mshe23.tga",
        "Mshe27.tga",
        "Mshe28.TGA",
        "Mshe2a.tga",
        "Mshe31.tga",
        "Mshe400.TGA",
        "Mshe50.tga",
        "Mshe60.tga",
        "Mshe96.tga",
        "Mshe97.tga",
        "Mshe98.TGA",
        "Mshe99.TGA",
        "Mshe9b.TGA",
        "Mshe9c.TGA",
        "Mshe9d.TGA",
        "Mshe_1.tga",
        "MsMask.bmp",
        "MsMaskCelestial.bmp",
        "msmsms_2.TGA",
        "msxmas.smd"
      ],
      "smdFiles": [
        "mec125.smd",
        "mec128.smd",
        "Mecanico.smd",
        "Mecanico1.smd",
        "Mecanico2.smd",
        "mech301.smd",
        "MechLPK.smd",
        "mecvip.smd",
        "ms-hair1.smd",
        "ms-hair2.smd",
        "MS-HairS.smd",
        "ms150.smd",
        "ms_dragon.smd",
        "mshair.smd",
        "msxmas.smd"
      ],
      "defaultModel": "mec125.smd"
    },
    {
      "id": "pikeman",
      "name": "Pikeman",
      "base": "Pikeman.smd",
      "files": [
        "pik125.smd",
        "pik128.smd",
        "pike301.smd",
        "pike4a.tga",
        "pike4b.tga",
        "pike4c.tga",
        "pike_054_01.tga",
        "pike_054_02.tga",
        "pike_054_03.tga",
        "pike_055_01.tga",
        "pike_055_02.tga",
        "pike_055_03.tga",
        "pike_108_01.tga",
        "pike_108_02.tga",
        "pike_108_03.tga",
        "pike_108_58.tga",
        "pike_108_59.tga",
        "pike_108_60.tga",
        "pike_125_01.tga",
        "pike_125_02.tga",
        "pike_125_03.tga",
        "pike_125_04.tga",
        "pike_125_05.tga",
        "pike_125_06.tga",
        "pike_125_07.tga",
        "pike_125_08.tga",
        "pike_125_09.tga",
        "pike_12b_01.tga",
        "pike_12b_02.tga",
        "pike_12b_03.tga",
        "pike_12z_z1.tga",
        "pike_12z_z2.tga",
        "pike_12z_z3.tga",
        "pike_166_01.tga",
        "pike_166_02.tga",
        "pike_166_03.tga",
        "pike_Argen_WC.tga",
        "pike_Argnt_WC.tga",
        "pike_Bahia_WC.tga",
        "pike_Brazil_WC.tga",
        "pike_Brzil_WC.tga",
        "pike_chels_EG.tga",
        "pike_Chile_WC.tga",
        "pike_chinadress.tga",
        "pike_Colom_WC.tga",
        "pike_exc_01.tga",
        "pike_exc_02.tga",
        "pike_exc_03.tga",
        "pike_Franc_WC.tga",
        "pike_France_WC.tga",
        "pike_Germa_WC.tga",
        "pike_hanbok01.tga",
        "pike_hanbok02.tga",
        "pike_Holla_WC.tga",
        "pike_Italy_WC.tga",
        "pike_Japan_WC.tga",
        "pike_kimono.tga",
        "pike_lpk_01.tga",
        "pike_lpk_02.tga",
        "pike_lpk_03.tga",
        "pike_magic_103_01.tga",
        "pike_magic_103_02.tga",
        "pike_magic_103_03.tga",
        "pike_magic_145_01.tga",
        "pike_magic_145_02.tga",
        "pike_magic_145_03.tga",
        "pike_magic_455_01.tga",
        "pike_magic_455_02.tga",
        "pike_magic_455_03.tga",
        "pike_magic_x55_01.tga",
        "pike_magic_x55_02.tga",
        "pike_magic_x55_03.tga",
        "pike_manch_EG.tga",
        "pike_Mexic_WC.tga",
        "pike_P_han.tga",
        "pike_Peru_WC.tga",
        "pike_Peruu_WC.tga",
        "pike_Pinoy_WC.tga",
        "pike_Portu_WC.tga",
        "pike_pugi.tga",
        "pike_rpt_01.tga",
        "pike_rpt_02.tga",
        "pike_rpt_03.tga",
        "pike_Santa.tga",
        "pike_Santa_G.tga",
        "pike_soldier_B.tga",
        "pike_Spain_WC.tga",
        "pike_swim.tga",
        "pike_TMUSA_WC.tga",
        "pike_traje_U.tga",
        "pike_trajeMA.tga",
        "pike_Vietn_WC.tga",
        "pike_WC.bmp",
        "pike_WC.tga",
        "pike_wmelon.tga",
        "pikeKT_01.tga",
        "pikeKT_01b.tga",
        "pikeKT_01c.tga",
        "pikeKT_02.tga",
        "pikeKT_02b.tga",
        "pikeKT_02c.tga",
        "pikeKT_03.tga",
        "pikeKT_03b.tga",
        "PikeLPK.smd",
        "Pikeman.smd",
        "Pikeman1.smd",
        "Pikeman2.smd",
        "pikesb_01.tga",
        "pikesb_01b.tga",
        "pikesb_01c.tga",
        "pikesb_02.tga",
        "pikesb_02b.tga",
        "pikesb_02c.tga",
        "pikesb_03.tga",
        "pikesb_03b.tga",
        "pikeSF_01.tga",
        "pikeSF_01b.tga",
        "pikeSF_01c.tga",
        "pikeSF_02.tga",
        "pikeSF_02b.tga",
        "pikeSF_02c.tga",
        "pikeSF_03.tga",
        "pikeSF_03b.tga",
        "pikeSF_11b.tga",
        "pikeSF_11c.tga",
        "pikeSF_12b.tga",
        "pikeSF_12c.tga",
        "pikeSF_13b.tga",
        "pikeSG_01.tga",
        "pikeSG_01b.tga",
        "pikeSG_01c.tga",
        "pikeSG_02.tga",
        "pikeSG_02b.tga",
        "pikeSG_02c.tga",
        "pikeSG_03.tga",
        "pikeSG_03b.tga",
        "pikesy_01.tga",
        "pikesy_01b.tga",
        "pikesy_01c.tga",
        "pikesy_02.tga",
        "pikesy_02b.tga",
        "pikesy_02c.tga",
        "pikesy_03.tga",
        "pikesy_03b.tga",
        "pikesz_01.tga",
        "pikesz_01b.tga",
        "pikesz_01c.tga",
        "pikesz_02.tga",
        "pikesz_02b.tga",
        "pikesz_02c.tga",
        "pikesz_03.tga",
        "pikesz_03b.tga",
        "pikvip.smd",
        "ps-1.Bmp",
        "PS-1751.bmp",
        "ps-1752.bmp",
        "ps-2.bmp",
        "ps-3.bmp",
        "ps-hair1.smd",
        "ps-hair2.smd",
        "PS-HairS.smd",
        "PS-Vahvel-175.smd",
        "ps01.bmp",
        "ps02.bmp",
        "ps03.bmp",
        "ps150.bmp",
        "ps150.smd",
        "ps1504.Bmp",
        "ps151.Bmp",
        "ps153.bmp",
        "Ps61.bmp",
        "Ps62.bmp",
        "Ps63.bmp",
        "PS74.bmp",
        "ps75.bmp",
        "PS76.bmp",
        "ps_gpt_1.tga",
        "pshair.smd",
        "PsMsk.bmp",
        "pspsps_1.TGA",
        "pspsps_2.TGA",
        "pspsps_3.TGA",
        "psxmas.smd"
      ],
      "smdFiles": [
        "pik125.smd",
        "pik128.smd",
        "pike301.smd",
        "PikeLPK.smd",
        "Pikeman.smd",
        "Pikeman1.smd",
        "Pikeman2.smd",
        "pikvip.smd",
        "ps-hair1.smd",
        "ps-hair2.smd",
        "PS-HairS.smd",
        "PS-Vahvel-175.smd",
        "ps150.smd",
        "pshair.smd",
        "psxmas.smd"
      ],
      "defaultModel": "Pikeman1.smd"
    },
    {
      "id": "archer",
      "name": "Archer",
      "base": "Archer.smd",
      "files": [
        "ar_054_01.tga",
        "ar_054_02.tga",
        "ar_055_01.tga",
        "ar_055_02.tga",
        "ar_0599.tga",
        "ar_05MA.tga",
        "ar_108_01.tga",
        "ar_108_02.tga",
        "ar_108_02_00c.tga",
        "ar_108_59.tga",
        "ar_108_60.tga",
        "ar_125_01.tga",
        "ar_125_02.tga",
        "ar_125_03.tga",
        "ar_125_04.tga",
        "ar_125_05.tga",
        "ar_125_06.tga",
        "ar_12b_01.tga",
        "ar_12b_02.tga",
        "ar_12z_z1.tga",
        "ar_12z_z2.tga",
        "ar_166_01.tga",
        "ar_166_02.tga",
        "ar_Aquila.tga",
        "ar_Argen_WC.tga",
        "ar_Argnt_WC.tga",
        "ar_Bahia_WC.tga",
        "ar_blackwedding.tga",
        "ar_bone.tga",
        "ar_Brazil_WC.tga",
        "ar_broyale.tga",
        "ar_Brzil_WC.tga",
        "ar_Chile_WC.tga",
        "ar_chinadress.tga",
        "ar_Colom_WC.tga",
        "ar_corvus.tga",
        "ar_Cygnus.tga",
        "ar_dr1.bmp",
        "ar_dragao.tga",
        "ar_drago2.tga",
        "ar_exc_01.tga",
        "ar_exc_02.tga",
        "ar_Franc_WC.tga",
        "ar_Germa_WC.tga",
        "ar_hanbok01.tga",
        "ar_hanbok02.tga",
        "ar_Holla_WC.tga",
        "ar_Italy_WC.tga",
        "ar_Japan_WC.tga",
        "ar_juninwedding.tga",
        "ar_kimono.tga",
        "ar_magic_103_01.tga",
        "ar_magic_103_02.tga",
        "ar_magic_103_02_00c.tga",
        "ar_magic_455_01.tga",
        "ar_magic_455_02.tga",
        "ar_magic_x55_01.tga",
        "ar_magic_x55_02.tga",
        "ar_mechaniA.tga",
        "ar_mechanib.tga",
        "ar_mechanic.tga",
        "ar_Mexic_WC.tga",
        "ar_Obsidi.tga",
        "ar_P_han.tga",
        "ar_Peru_WC.tga",
        "ar_Peruu_WC.tga",
        "ar_Pinoy_WC.tga",
        "ar_Portu_WC.tga",
        "ar_pugi.tga",
        "ar_pump.tga",
        "ar_qupA.tga",
        "ar_qupc.tga",
        "ar_qupi.tga",
        "ar_qupy.tga",
        "ar_rpt_01.tga",
        "ar_rpt_02.tga",
        "ar_Santa.tga",
        "ar_Santa2.tga",
        "ar_Santa_G.tga",
        "ar_schoollook_A.tga",
        "ar_schoollook_B.tga",
        "ar_soldier_A.tga",
        "ar_soldier_B.tga",
        "ar_soldier_C.tga",
        "ar_Spain_WC.tga",
        "ar_swim.tga",
        "ar_TMUSA_WC.tga",
        "ar_Vietn_WC.tga",
        "ar_WC.bmp",
        "ar_WC.tga",
        "ar_wedinC.tga",
        "ar_weding.tga",
        "ar_whiteday.tga",
        "ar_wmelon.tga",
        "arc125.smd",
        "arc128.smd",
        "arc4a.tga",
        "arc4b.tga",
        "arc_gap_001_01.TGA",
        "arc_gap_001_02.TGA",
        "arc_gap_0201.tga",
        "arc_gap_0202.tga",
        "arc_gap_0203.tga",
        "arc_gap_0204.tga",
        "arc_gap_0205.tga",
        "arc_gap_0206.tga",
        "arch301.smd",
        "arch_manch_CR.tga",
        "Archer.smd",
        "Archer1.smd",
        "Archer2.smd",
        "ArchivoTmp.tga",
        "ArcMask.tga",
        "ArcMaskCelestial.tga",
        "arcosuicidePT(FreeCell).bmp",
        "arcvip.smd"
      ],
      "smdFiles": [
        "arc125.smd",
        "arc128.smd",
        "arch301.smd",
        "Archer.smd",
        "Archer1.smd",
        "Archer2.smd",
        "arcvip.smd"
      ],
      "defaultModel": "arc125.smd"
    },
    {
      "id": "atalanta",
      "name": "Atalanta",
      "base": "Atalanta.smd",
      "files": [
        "at_dragon2.tga",
        "at_gpt_1.tga",
        "ata-02.bmp",
        "Ata-175-InFernoPT.smd",
        "Ata-175.bmp",
        "Ata-175105.tga",
        "ata-hair1.smd",
        "ata-hair2.smd",
        "ATA-HairS.smd",
        "ata105.bmp",
        "ata125.smd",
        "ata126.bmp",
        "ata126.tga",
        "Ata128.smd",
        "ata150.BMP",
        "ata150.smd",
        "ata152.bmp",
        "ata152a.Bmp",
        "ata152b.tga",
        "ata175.bmp",
        "ata301.smd",
        "ata734.bmp",
        "atahair.smd",
        "atal01.BMP",
        "atal01_00c.BMP",
        "atal02.BMP",
        "atal02_01c.BMP",
        "atal11.BMP",
        "atal12.BMP",
        "atal36.bmp",
        "atal42.bmp",
        "atal4a.tga",
        "atal4b.tga",
        "atal91.bmp",
        "atal92.bmp",
        "atal_0599.tga",
        "atal_05MA.tga",
        "atal_108_01.tga",
        "atal_108_01_00c.tga",
        "atal_108_02.tga",
        "atal_125_01.tga",
        "atal_125_02.tga",
        "atal_125_03.tga",
        "atal_125_04.tga",
        "atal_125_05.tga",
        "atal_125_06.tga",
        "atal_12b_01.tga",
        "atal_12b_02.tga",
        "atal_12z_z1.tga",
        "atal_12z_z2.tga",
        "atal_166_01.tga",
        "atal_166_02.tga",
        "atal_Aquila.tga",
        "atal_Argen_WC.tga",
        "atal_Argnt_WC.tga",
        "atal_Bahia_WC.tga",
        "atal_blackwedding.tga",
        "atal_Brazil_WC.tga",
        "atal_broyale.tga",
        "atal_Brzil_WC.tga",
        "atal_chels_EG.tga",
        "atal_Chile_WC.tga",
        "atal_chinadress.tga",
        "atal_Colom_WC.tga",
        "atal_corvus.tga",
        "atal_Cygnus.tga",
        "atal_dragao.tga",
        "atal_exc_01.tga",
        "atal_exc_02.tga",
        "atal_Franc_WC.tga",
        "atal_Germa_WC.tga",
        "atal_hanbok01.tga",
        "atal_hanbok02.tga",
        "atal_Holla_WC.tga",
        "atal_Italy_WC.tga",
        "atal_Japan_WC.tga",
        "atal_juninwedding.tga",
        "atal_kimono.tga",
        "atal_magic_103_01.tga",
        "atal_magic_103_01_00c.tga",
        "atal_magic_103_02.tga",
        "atal_magic_455_01.tga",
        "atal_magic_455_02.tga",
        "atal_magic_x55_01.tga",
        "atal_magic_x55_02.tga",
        "atal_manch_EG.tga",
        "atal_mechaniA.tga",
        "atal_mechanib.tga",
        "atal_mechanic.tga",
        "atal_Mexic_WC.tga",
        "atal_Obsidi.tga",
        "atal_P_han.tga",
        "atal_Peru_WC.tga",
        "atal_Peruu_WC.tga",
        "atal_Pinoy_WC.tga",
        "atal_Portu_WC.tga",
        "atal_pugi.tga",
        "atal_qupA.tga",
        "atal_qupy.tga",
        "atal_rpt_01.tga",
        "atal_rpt_02.tga",
        "atal_Santa.tga",
        "atal_Santa2.tga",
        "atal_Santa_G.tga",
        "atal_schoollook_A.tga",
        "atal_schoollook_B.tga",
        "atal_soldier_A.tga",
        "atal_soldier_B.tga",
        "atal_soldier_C.tga",
        "atal_Spain_WC.tga",
        "atal_Swim.tga",
        "atal_TMUSA_WC.tga",
        "atal_Vietn_WC.tga",
        "atal_WC.bmp",
        "atal_WC.tga",
        "atal_weddinC.tga",
        "atal_wedding.tga",
        "atal_whiteday.tga",
        "atal_wmelon.tga",
        "Atalanta.smd",
        "Atalanta1.smd",
        "Atalanta2.smd",
        "atalKT_01.tga",
        "atalKT_01_00c.tga",
        "atalKT_01b.tga",
        "atalKT_01c.tga",
        "atalKT_02.tga",
        "atalKT_02b.tga",
        "atalKT_02c.tga",
        "ATALLPK.smd",
        "ATALLPK1.TGA",
        "ATALLPK2.TGA",
        "atalsb_01.tga",
        "atalsb_01_00c.tga",
        "atalsb_01b.tga",
        "atalsb_01c.tga",
        "atalsb_02.tga",
        "atalsb_02b.tga",
        "atalsb_02c.tga",
        "atalSF_01.tga",
        "atalSF_01_00c.tga",
        "atalSF_01b.tga",
        "atalSF_01c.tga",
        "atalSF_02.tga",
        "atalSF_02b.tga",
        "atalSF_02c.tga",
        "atalSF_11b.tga",
        "atalSF_11c.tga",
        "atalSF_12b.tga",
        "atalSF_12c.tga",
        "atalSG_01.tga",
        "atalSG_01_00c.tga",
        "atalSG_01b.tga",
        "atalSG_01c.tga",
        "atalSG_02.tga",
        "atalSG_02b.tga",
        "atalSG_02c.tga",
        "atalsy_01.tga",
        "atalsy_01_00c.tga",
        "atalsy_01b.tga",
        "atalsy_01c.tga",
        "atalsy_02.tga",
        "atalsy_02b.tga",
        "atalsy_02c.tga",
        "atalsz_01.tga",
        "atalsz_01_00c.tga",
        "atalsz_01b.tga",
        "atalsz_01c.tga",
        "atalsz_02.tga",
        "atalsz_02b.tga",
        "atalsz_02c.tga",
        "ataly2.bmp",
        "atalz2.bmp",
        "AtaMask.BMP",
        "AtaMask_Celestial.BMP",
        "atavip.smd",
        "ataxmas.smd"
      ],
      "smdFiles": [
        "Ata-175-InFernoPT.smd",
        "ata-hair1.smd",
        "ata-hair2.smd",
        "ATA-HairS.smd",
        "ata125.smd",
        "Ata128.smd",
        "ata150.smd",
        "ata301.smd",
        "atahair.smd",
        "Atalanta.smd",
        "Atalanta1.smd",
        "Atalanta2.smd",
        "ATALLPK.smd",
        "atavip.smd",
        "ataxmas.smd"
      ],
      "defaultModel": "Ata-175-InFernoPT.smd"
    },
    {
      "id": "magician",
      "name": "Magician",
      "base": "Mago.smd",
      "files": [
        "Mago.smd",
        "mago0001.TGA",
        "mago0002.TGA",
        "Mago1.smd",
        "Mago12.smd",
        "mago170.smd",
        "mago17y.smd",
        "Mago2.smd",
        "magoa.smd",
        "mg-hair1.smd",
        "mg-hair2.smd",
        "mg105b.bmp",
        "mg106b.bmp",
        "mg126b.bmp",
        "mg_dragon.smd",
        "mgdrag.BMP",
        "mghair.smd",
        "MgMaskCelestial.bmp",
        "MgMsk.bmp",
        "MGS-HairS.smd",
        "mgs301.smd",
        "mgxmas.smd"
      ],
      "smdFiles": [
        "Mago.smd",
        "Mago1.smd",
        "Mago12.smd",
        "mago170.smd",
        "mago17y.smd",
        "Mago2.smd",
        "magoa.smd",
        "mg-hair1.smd",
        "mg-hair2.smd",
        "mg_dragon.smd",
        "mghair.smd",
        "MGS-HairS.smd",
        "mgs301.smd",
        "mgxmas.smd"
      ],
      "defaultModel": "Mago1.smd"
    },
    {
      "id": "priestess",
      "name": "Priestess",
      "base": "Sacer.smd",
      "files": [
        "pr100_yun01.tga",
        "pr100_yun02.tga",
        "pr100_yun02_00c.tga",
        "pr100_yun91.tga",
        "pr100_yun92.tga",
        "pr123_yun01.tga",
        "pr123_yun02.tga",
        "pr200_yun01.tga",
        "pr200_yun02.tga",
        "pr223_yun01.tga",
        "pr223_yun02.tga",
        "pr306_yun01.tga",
        "pr306_yun02.tga",
        "pr307_yun01.tga",
        "pr307_yun02.tga",
        "pr_054_01.tga",
        "pr_054_02.tga",
        "pr_055_01.tga",
        "pr_055_02.tga",
        "pr_0599.tga",
        "pr_05MA.tga",
        "pr_108_01.tga",
        "pr_108_02.tga",
        "pr_108_02_00c.tga",
        "pr_108_59.tga",
        "pr_108_60.tga",
        "pr_10b_01.tga",
        "pr_10b_02.tga",
        "pr_125_01.tga",
        "pr_125_02.tga",
        "pr_125_03.tga",
        "pr_125_04.tga",
        "pr_125_05.tga",
        "pr_125_06.tga",
        "pr_12z_E1.tga",
        "pr_12z_E2.tga",
        "pr_166_01.tga",
        "pr_166_02.tga",
        "pr_908_01.tga",
        "pr_908_02.tga",
        "pr_Aquila.tga",
        "pr_Argen_WC.tga",
        "pr_Argnt_WC.tga",
        "pr_Awim.tga",
        "pr_Bahia_WC.tga",
        "pr_blackwedding.tga",
        "pr_Brazil_WC.tga",
        "pr_broyale.tga",
        "pr_Brzil_WC.tga",
        "pr_chels_EG.tga",
        "pr_Chile_WC.tga",
        "pr_chinadress.tga",
        "pr_Colom_WC.tga",
        "pr_corvus.tga",
        "pr_Cygnus.tga",
        "pr_dragao.tga",
        "pr_drago1.tga",
        "pr_drago2.bmp",
        "pr_dragon.smd",
        "pr_exc_01.tga",
        "pr_exc_02.tga",
        "pr_Franc_WC.tga",
        "pr_Germa_WC.tga",
        "pr_hanbok01.tga",
        "pr_hanbok02.tga",
        "pr_Holla_WC.tga",
        "pr_Italy_WC.tga",
        "pr_Japan_WC.tga",
        "pr_juninwedding.tga",
        "pr_kimono.tga",
        "pr_magic_103_01.tga",
        "pr_magic_103_02.tga",
        "pr_magic_103_02_00c.tga",
        "pr_magic_455_01.tga",
        "pr_magic_455_02.tga",
        "pr_magic_exc_01.tga",
        "pr_magic_exc_02.tga",
        "pr_magic_x55_01.tga",
        "pr_magic_x55_02.tga",
        "pr_manch_EG.tga",
        "pr_mechaniA.tga",
        "pr_mechanib.tga",
        "pr_mechanic.tga",
        "pr_Mexic_WC.tga",
        "pr_Obsidi.tga",
        "pr_P_han.tga",
        "pr_Peru_WC.tga",
        "pr_Peruu_WC.tga",
        "pr_Pinoy_WC.tga",
        "pr_Portu_WC.tga",
        "pr_pugi.tga",
        "pr_pugi.tga.tga",
        "pr_qupA.tga",
        "pr_qupy.tga",
        "pr_rpt_01.tga",
        "pr_rpt_02.tga",
        "pr_Santa.tga",
        "pr_Santa2.tga",
        "pr_Santa_G.tga",
        "pr_schoollook_A.tga",
        "pr_schoollook_B.tga",
        "pr_soldier_A.tga",
        "pr_soldier_B.tga",
        "pr_soldier_C.tga",
        "pr_Spain_WC.tga",
        "pr_swim.tga.tga",
        "pr_TMUSA_WC.tga",
        "pr_Vietn_WC.tga",
        "pr_WC.bmp",
        "pr_WC.tga",
        "pr_weddinC.tga",
        "pr_wedding.tga",
        "pr_whiteday.tga",
        "pr_wmelon.tga",
        "predator_m1.smd",
        "predator_m2.smd",
        "predator_m3.smd",
        "predator_m4.smd",
        "predator_m5.smd",
        "predator_m6.smd",
        "predator_m7.smd",
        "predator_m8.smd",
        "Premo-115--A.smd",
        "Premo-115--B.smd",
        "Premo-115--C.smd",
        "Premo-115--D.smd",
        "Premo-115--E.smd",
        "Premo-115--F.smd",
        "prExc.smd",
        "prExcX.smd",
        "pri125.smd",
        "pri128.smd",
        "prKT_01.tga",
        "prKT_01b.tga",
        "prKT_02.tga",
        "prKT_02b.tga",
        "prKT_03.tga",
        "PRLPK.smd",
        "PRLPK1.smd",
        "PRLPK_yun01.tga",
        "PRLPK_yun02.tga",
        "PRLPK_yun03.tga",
        "PRLPK_yun04.tga",
        "prs-hair1.smd",
        "PRS-HairS.smd",
        "prsb_01.tga",
        "prsb_01b.tga",
        "prsb_02.tga",
        "prsb_02b.tga",
        "prsb_03.tga",
        "prSF_01.tga",
        "prSF_01b.tga",
        "prSF_02.tga",
        "prSF_02b.tga",
        "prSF_03.tga",
        "prSF_11b.tga",
        "prSF_12b.tga",
        "prSG_01.tga",
        "prSG_01b.tga",
        "prSG_02.tga",
        "prSG_02b.tga",
        "prSG_03.tga",
        "prss-hair2.smd",
        "prsshair.smd",
        "prst301.smd",
        "prsxmas.smd",
        "prsy_01.tga",
        "prsy_01b.tga",
        "prsy_02.tga",
        "prsy_02b.tga",
        "prsy_03.tga",
        "prsz_01.tga",
        "prsz_01b.tga",
        "prsz_02.tga",
        "prsz_02b.tga",
        "prsz_03.tga",
        "Sacer.smd",
        "Sacer1.smd",
        "Sacer2.smd",
        "sacer_01.TGA",
        "sacer_02.TGA"
      ],
      "smdFiles": [
        "pr_dragon.smd",
        "predator_m1.smd",
        "predator_m2.smd",
        "predator_m3.smd",
        "predator_m4.smd",
        "predator_m5.smd",
        "predator_m6.smd",
        "predator_m7.smd",
        "predator_m8.smd",
        "Premo-115--A.smd",
        "Premo-115--B.smd",
        "Premo-115--C.smd",
        "Premo-115--D.smd",
        "Premo-115--E.smd",
        "Premo-115--F.smd",
        "prExc.smd",
        "prExcX.smd",
        "pri125.smd",
        "pri128.smd",
        "PRLPK.smd",
        "PRLPK1.smd",
        "prs-hair1.smd",
        "PRS-HairS.smd",
        "prss-hair2.smd",
        "prsshair.smd",
        "prst301.smd",
        "prsxmas.smd",
        "Sacer.smd",
        "Sacer1.smd",
        "Sacer2.smd"
      ],
      "defaultModel": "Sacer1.smd"
    },
    {
      "id": "assassin",
      "name": "Assassin",
      "base": "Assasin.smd",
      "files": [
        "as_0599.tga",
        "as_05MA.tga",
        "as_Aquila.tga",
        "as_Argen_WC.tga",
        "as_blackwedding.tga",
        "as_Brazil_WC.tga",
        "as_broyale.tga",
        "as_Chile_WC.tga",
        "as_chinadress.tga",
        "as_Colom_WC.tga",
        "as_corvus.tga",
        "as_Cygnus.tga",
        "as_Franc_WC.tga",
        "as_Germa_WC.tga",
        "as_gpt_1.tga",
        "as_hanbok01.tga",
        "as_hanbok02.tga",
        "as_Holla_WC.tga",
        "as_Italy_WC.tga",
        "as_Japan_WC.tga",
        "as_juninwedding.tga",
        "as_kimono.tga",
        "as_mechanib.tga",
        "as_mechanic.tga",
        "as_Mexic_WC.tga",
        "as_Obsidi.tga",
        "as_P_han.tga",
        "as_Peru_WC.tga",
        "as_Pinoy_WC.tga",
        "as_Portu_WC.tga",
        "as_qupA.tga",
        "as_qupi.tga",
        "as_qupy.tga",
        "as_Santa.tga",
        "as_Santa2.tga",
        "as_Santa_G.tga",
        "as_schoollook_A.tga",
        "as_schoollook_B.tga",
        "as_soldier_A.tga",
        "as_soldier_B.tga",
        "as_soldier_C.tga",
        "as_Spain_WC.tga",
        "as_TMUSA_WC.tga",
        "as_Vietn_WC.tga",
        "as_WC.tga",
        "as_weddinC.tga",
        "as_wedding.tga",
        "as_whiteday.tga",
        "as_wmelon.tga",
        "ASS-HairS.smd",
        "ass301.smd",
        "ass_dragon.smd",
        "Ass_swim.tga",
        "Assasin.smd",
        "Assasin1.smd",
        "Assasin2.smd",
        "assdr1.tga",
        "assdr2.tga",
        "assdr3.tga",
        "assdr4.tga",
        "asshair.smd",
        "assxmas.smd"
      ],
      "smdFiles": [
        "ASS-HairS.smd",
        "ass301.smd",
        "ass_dragon.smd",
        "Assasin.smd",
        "Assasin1.smd",
        "Assasin2.smd",
        "asshair.smd",
        "assxmas.smd"
      ],
      "defaultModel": "ASS-HairS.smd"
    },
    {
      "id": "shaman",
      "name": "Shaman",
      "base": "Shaman.smd",
      "files": [
        "sh-hair.smd",
        "sh-hair1.smd",
        "sh-hair2.smd",
        "sh_Argen_WC.tga",
        "sh_Brazil_WC.tga",
        "sh_Chile_WC.tga",
        "sh_chinadress.tga",
        "sh_Colom_WC.tga",
        "sh_dr1.tga",
        "sh_dr2.tga",
        "sh_dr3.tga",
        "sh_dr4.tga",
        "sh_dragon.smd",
        "sh_Franc_WC.tga",
        "sh_Germa_WC.tga",
        "sh_hanbok01.tga",
        "sh_hanbok02.tga",
        "sh_Holla_WC.tga",
        "sh_Italy_WC.tga",
        "sh_Japan_WC.tga",
        "sh_kimono.tga",
        "sh_Mexic_WC.tga",
        "sh_P_han.tga",
        "sh_Peru_WC.tga",
        "sh_Pinoy_WC.tga",
        "sh_Portu_WC.tga",
        "sh_Santa.tga",
        "sh_Santa_G.tga",
        "sh_soldier_B.tga",
        "sh_Spain_WC.tga",
        "sh_swim.tga",
        "sh_TMUSA_WC.tga",
        "sh_traje_U.tga",
        "sh_trajeMA.tga",
        "sh_Vietn_WC.tga",
        "sh_WC.tga",
        "sh_wmelon.tga",
        "Shaman.smd",
        "Shaman1.smd",
        "Shaman2.smd",
        "SharinganFS.smd",
        "Shark1.smd",
        "Shark2.smd",
        "Shark3.smd",
        "Shark4.smd",
        "Shark5.smd",
        "Shark6.smd",
        "Shark7.smd",
        "Shark8.smd",
        "sheepHairBlak.tga",
        "sheepHairtint.tga",
        "shhair.smd",
        "shm301.smd",
        "Shura_MA.smd",
        "shxmas.smd"
      ],
      "smdFiles": [
        "sh-hair.smd",
        "sh-hair1.smd",
        "sh-hair2.smd",
        "sh_dragon.smd",
        "Shaman.smd",
        "Shaman1.smd",
        "Shaman2.smd",
        "SharinganFS.smd",
        "Shark1.smd",
        "Shark2.smd",
        "Shark3.smd",
        "Shark4.smd",
        "Shark5.smd",
        "Shark6.smd",
        "Shark7.smd",
        "Shark8.smd",
        "shhair.smd",
        "shm301.smd",
        "Shura_MA.smd",
        "shxmas.smd"
      ],
      "defaultModel": "Shaman1.smd"
    }
  ]
}